skunk/__init__.py
skunk/version.py
skunk-1.3.0.dist-info/LICENSE
skunk-1.3.0.dist-info/METADATA
skunk-1.3.0.dist-info/WHEEL
skunk-1.3.0.dist-info/top_level.txt
skunk-1.3.0.dist-info/RECORD
