Metadata-Version: 2.1
Name: skunk
Version: 1.3.0
Summary: Insert SVGs into matplotlib figures
Home-page: https://github.com/whitead/skunk
Author: Andrew White
Author-email: andrew.white@rochester.edu
License: MIT
Classifier: Programming Language :: Python :: 3
Classifier: License :: OSI Approved :: MIT License
Classifier: Operating System :: OS Independent
Classifier: Framework :: Matplotlib
License-File: LICENSE
Requires-Dist: matplotlib
